dendritic/__init__.py
dendritic/py.typed
dendritic-0.1.0.dist-info/METADATA
dendritic-0.1.0.dist-info/WHEEL
dendritic-0.1.0.dist-info/licenses/LICENSE
dendritic-0.1.0.dist-info/RECORD
